modelq/__init__.py
modelq/app/__init__.py
modelq/app/api/server.py
modelq/app/base.py
modelq/app/cli/__init__.py
modelq/app/cli/main.py
modelq/app/middleware/__init__.py
modelq/app/middleware/base.py
modelq/app/redis_retry.py
modelq/app/sentry.py
modelq/app/tasks/__init__.py
modelq/app/tasks/base.py
modelq/app/utils/__init__.py
modelq/app/utils/base64.py
modelq/exceptions.py
modelq-1.0.9.dist-info/METADATA
modelq-1.0.9.dist-info/WHEEL
modelq-1.0.9.dist-info/entry_points.txt
modelq-1.0.9.dist-info/licenses/LICENSE
modelq-1.0.9.dist-info/RECORD
