Metadata-Version: 2.4
Name: modelq
Version: 1.0.9
Summary: Celery-like task queue for ML inference.
License-File: LICENSE
Author: Tanmaypatil123
Author-email: tanmay@modelslab.com
Requires-Python: >=3.9,<4.0
Classifier: Programming Language :: Python :: 3
Classifier: Programming Language :: Python :: 3.9
Classifier: Programming Language :: Python :: 3.10
Classifier: Programming Language :: Python :: 3.11
Classifier: Programming Language :: Python :: 3.12
Classifier: Programming Language :: Python :: 3.13
Classifier: Programming Language :: Python :: 3.14
Provides-Extra: sentry
Requires-Dist: click (>=8.0.0,<9.0.0)
Requires-Dist: fakeredis (>=2.33.0,<3.0.0)
Requires-Dist: fastapi (>=0.115.12,<0.116.0)
Requires-Dist: nvidia-ml-py (>=12.0.0,<13.0.0)
Requires-Dist: psutil (>=5.9.0,<6.0.0)
Requires-Dist: pydantic (>=2.11.5,<3.0.0)
Requires-Dist: redis (>=4.0.0,<5.0.0)
Requires-Dist: sentry-sdk (>=2.0.0,<3.0.0) ; extra == "sentry"
Requires-Dist: typer (>=0.16.0,<0.17.0)
Requires-Dist: uvicorn (>=0.34.2,<0.35.0)
